LICENSE
MANIFEST.in
README.rst
setup.cfg
setup.py
channels_framework/__init__.py
channels_framework/bindings.py
channels_framework/mixins.py
channels_framework/settings.py
channels_framework/urls.py
channelsrestframework.egg-info/PKG-INFO
channelsrestframework.egg-info/SOURCES.txt
channelsrestframework.egg-info/dependency_links.txt
channelsrestframework.egg-info/requires.txt
channelsrestframework.egg-info/top_level.txt
tests/__init__.py
tests/models.py
tests/test_bindings.py
tests/test_settings.py
tests/migrations/0001_initial.py
tests/migrations/__init__.py