Metadata-Version: 1.1
Name: channelsrestframework
Version: 0.1.4
Summary: Build a RESTful API on top of WebSockets using Django channels and Django Rest Framework.
Home-page: https://github.com/madra/channels-rest-framework
Author: Madra David
Author-email: david@madradavid.com
License: BSD
Download-URL: https://github.com/madra/channels-rest-framework/tarball/0.1
Platform: UNKNOWN
Classifier: Development Status :: 5 - Production/Stable
Classifier: Environment :: Web Environment
Classifier: Framework :: Django
Classifier: Intended Audience :: Developers
Classifier: License :: OSI Approved :: BSD License
Classifier: Operating System :: OS Independent
Classifier: Programming Language :: Python
Classifier: Programming Language :: Python :: 3
Classifier: Topic :: Internet :: WWW/HTTP
